{"alternativeYields":{"wardenMarket":{"label":"Market","platform":"Warden","href":"https://app.warden.vote/boosts/market/"},"wardenPledge":{"label":"Pledge","platform":"Warden","href":"https://app.warden.vote/boosts/pledge/"},"asdcrvDelegation":{"label":"asdCRV Delegation","platform":"Concentator","href":"https://concentrator.aladdin.club/#/vault"}},"veSdtTotalSupply":34087239.512492426,"locked":42620031.005632795,"lockedInUsd":7996204.745830755,"percentLocked":61.756656123814324,"averageLockInYears":3.1991754776515626,"apr":8.614229132425567,"voteBoosterVeSdt":1069824.8399437151}