{"alternativeYields":{"wardenMarket":{"label":"Market","platform":"Warden","href":"https://app.warden.vote/boosts/market/"},"wardenPledge":{"label":"Pledge","platform":"Warden","href":"https://app.warden.vote/boosts/pledge/"},"asdcrvDelegation":{"label":"asdCRV Delegation","platform":"Concentator","href":"https://concentrator.aladdin.club/#/vault"}},"veSdtTotalSupply":"22400014998391352749799590","locked":"31881360319160850573539318","lockedInUsd":8066878.868050472,"vestedInUsd":1759131.789813528,"percentLocked":49.467808469642236,"averageLockInYears":2.810421484421897,"apr":0,"voteBoosterVeSdt":1037394.5712476601,"lockersTotalWeight":"7803754220088782657343936000000000000000000","stratsTotalWeight":"7754645450468960588778912000000000000000000"}